donoratlas/__init__.py
donoratlas/addresses.py
donoratlas/names/__init__.py
donoratlas/names/names.py
donoratlas/names/parser.py
donoratlas/static/popular.txt
donoratlas/static/prefixes.json
donoratlas/static/states.json
donoratlas/static/unique_terms.txt
donoratlas/static/census_baby_names/NationalReadMe.pdf
donoratlas/static/census_baby_names/first_to_score.json
donoratlas/static/census_baby_names/yob1880.txt
donoratlas/static/census_baby_names/yob1881.txt
donoratlas/static/census_baby_names/yob1882.txt
donoratlas/static/census_baby_names/yob1883.txt
donoratlas/static/census_baby_names/yob1884.txt
donoratlas/static/census_baby_names/yob1885.txt
donoratlas/static/census_baby_names/yob1886.txt
donoratlas/static/census_baby_names/yob1887.txt
donoratlas/static/census_baby_names/yob1888.txt
donoratlas/static/census_baby_names/yob1889.txt
donoratlas/static/census_baby_names/yob1890.txt
donoratlas/static/census_baby_names/yob1891.txt
donoratlas/static/census_baby_names/yob1892.txt
donoratlas/static/census_baby_names/yob1893.txt
donoratlas/static/census_baby_names/yob1894.txt
donoratlas/static/census_baby_names/yob1895.txt
donoratlas/static/census_baby_names/yob1896.txt
donoratlas/static/census_baby_names/yob1897.txt
donoratlas/static/census_baby_names/yob1898.txt
donoratlas/static/census_baby_names/yob1899.txt
donoratlas/static/census_baby_names/yob1900.txt
donoratlas/static/census_baby_names/yob1901.txt
donoratlas/static/census_baby_names/yob1902.txt
donoratlas/static/census_baby_names/yob1903.txt
donoratlas/static/census_baby_names/yob1904.txt
donoratlas/static/census_baby_names/yob1905.txt
donoratlas/static/census_baby_names/yob1906.txt
donoratlas/static/census_baby_names/yob1907.txt
donoratlas/static/census_baby_names/yob1908.txt
donoratlas/static/census_baby_names/yob1909.txt
donoratlas/static/census_baby_names/yob1910.txt
donoratlas/static/census_baby_names/yob1911.txt
donoratlas/static/census_baby_names/yob1912.txt
donoratlas/static/census_baby_names/yob1913.txt
donoratlas-0.0.1.dist-info/LICENSE.md
donoratlas-0.0.1.dist-info/METADATA
donoratlas-0.0.1.dist-info/WHEEL
donoratlas-0.0.1.dist-info/top_level.txt
donoratlas-0.0.1.dist-info/RECORD
