Metadata-Version: 2.1
Name: donoratlas
Version: 0.0.1
Summary: DonorAtlas's helper library
Author: DonorAtlas
Author-email: DonorAtlas <aaron@donoratlas.com>
Maintainer-email: DonorAtlas <aaron@donoratlas.com>
License: GNU GENERAL PUBLIC LICENSE
Project-URL: Homepage, https://github.com/DonorAtlas/DonorAtlas
Classifier: Programming Language :: Python :: 3
Classifier: License :: OSI Approved :: MIT License
Classifier: Operating System :: OS Independent
Requires-Python: >=3.11
License-File: LICENSE.md
Requires-Dist: annotated-types==0.7.0
Requires-Dist: asttokens==2.4.1
Requires-Dist: click==8.1.7
Requires-Dist: cloudpickle==3.1.0
Requires-Dist: comm==0.2.2
Requires-Dist: dask==2024.10.0
Requires-Dist: dask-expr==1.1.16
Requires-Dist: debugpy==1.8.7
Requires-Dist: decorator==5.1.1
Requires-Dist: executing==2.1.0
Requires-Dist: fsspec==2024.10.0
Requires-Dist: human-name-compare==0.4.1
Requires-Dist: importlib-metadata==8.5.0
Requires-Dist: inflect==7.4.0
Requires-Dist: ipykernel==6.29.5
Requires-Dist: ipython==8.29.0
Requires-Dist: jedi==0.19.1
Requires-Dist: jupyter-client==8.6.3
Requires-Dist: jupyter-core==5.7.2
Requires-Dist: locket==1.0.0
Requires-Dist: matplotlib-inline==0.1.7
Requires-Dist: more-itertools==10.5.0
Requires-Dist: nameparser==1.1.3
Requires-Dist: nest-asyncio==1.6.0
Requires-Dist: nicknames==0.1.10
Requires-Dist: numpy==2.1.3
Requires-Dist: packaging==24.1
Requires-Dist: pandas==2.2.3
Requires-Dist: parso==0.8.4
Requires-Dist: partd==1.4.2
Requires-Dist: pexpect==4.9.0
Requires-Dist: platformdirs==4.3.6
Requires-Dist: postal==1.1.10
Requires-Dist: prompt-toolkit==3.0.48
Requires-Dist: psutil==6.1.0
Requires-Dist: ptyprocess==0.7.0
Requires-Dist: pure-eval==0.2.3
Requires-Dist: pyarrow==18.0.0
Requires-Dist: pydantic==2.9.2
Requires-Dist: pydantic-core==2.23.4
Requires-Dist: Pygments==2.18.0
Requires-Dist: python-dateutil==2.9.0.post0
Requires-Dist: pytz==2024.2
Requires-Dist: PyYAML==6.0.2
Requires-Dist: pyzmq==26.2.0
Requires-Dist: RapidFuzz==3.10.0
Requires-Dist: six==1.16.0
Requires-Dist: stack-data==0.6.3
Requires-Dist: swifter==1.4.0
Requires-Dist: tabulate==0.9.0
Requires-Dist: termcolor==2.5.0
Requires-Dist: toolz==1.0.0
Requires-Dist: tornado==6.4.1
Requires-Dist: tqdm==4.67.0
Requires-Dist: traitlets==5.14.3
Requires-Dist: typeguard==4.4.1
Requires-Dist: typing-extensions==4.12.2
Requires-Dist: tzdata==2024.2
Requires-Dist: wcwidth==0.2.13
Requires-Dist: zipp==3.20.2
